carla_client_unofficial-0.9.11.dist-info/top_level.txt
carla_client_unofficial-0.9.11.dist-info/RECORD
carla_client_unofficial-0.9.11.dist-info/METADATA
carla_client_unofficial-0.9.11.dist-info/WHEEL
carla_client_unofficial.libs/libtiff-b6eb22fb.so.5.2.0
carla_client_unofficial.libs/libpng16-ce74449f.so.16.37.0
carla_client_unofficial.libs/libjbig-78348776.so.2.0
carla_client_unofficial.libs/libz-745e0a09.so.1.2.7
carla_client_unofficial.libs/libjpeg-43436dd5.so.62.1.0
carla/command.py
carla/__init__.py
carla/libcarla.cpython-37m-x86_64-linux-gnu.so
