Metadata-Version: 2.1
Name: carla-client-unofficial
Version: 0.9.11
Summary: Python API for communicating with the CARLA server.
Home-page: https://github.com/carla-simulator/carla
Author: The CARLA team
Author-email: carla.simulator@gmail.com
License: MIT License
Platform: UNKNOWN
